memoizelabs/__init__.py
memoizelabs/client.py
memoizelabs-0.0.1.2.dist-info/LICENSE
memoizelabs-0.0.1.2.dist-info/METADATA
memoizelabs-0.0.1.2.dist-info/WHEEL
memoizelabs-0.0.1.2.dist-info/top_level.txt
memoizelabs-0.0.1.2.dist-info/RECORD
